{"true_labels": [{"name": "man0", "intervals": [{"start": 0, "end": 10000}]}, {"name": "man2", "intervals": [{"start": 10000, "end": 15000}]}, {"name": "man5", "intervals": [{"start": 15000, "end": 19000}]}, {"name": "man11", "intervals": [{"start": 19000, "end": 27000}, {"start": 35000, "end": 37000}]}, {"name": "woman2", "intervals": [{"start": 27000, "end": 35000}]}], "predicted_labels": ["start=0ms stop=1000ms SPEAKER_00", "start=1000ms stop=8000ms SPEAKER_00", "start=10000ms stop=13000ms SPEAKER_01", "start=15000ms stop=18000ms SPEAKER_02", "start=19000ms stop=19000ms SPEAKER_02", "start=19000ms stop=21000ms SPEAKER_03", "start=21000ms stop=26000ms SPEAKER_03", "start=26000ms stop=35000ms SPEAKER_04", "start=35000ms stop=36000ms SPEAKER_03", "start=36000ms stop=36000ms SPEAKER_03"], "accuracy": 0.9, "number_of_speakers": 5}