{"true_labels": [{"name": "woman3", "intervals": [{"start": 0, "end": 2000}, {"start": 2000, "end": 6000}, {"start": 6000, "end": 12000}]}, {"name": "man11", "intervals": [{"start": 12000, "end": 20000}]}, {"name": "man5", "intervals": [{"start": 20000, "end": 57000}]}, {"name": "woman2", "intervals": [{"start": 57000, "end": 60000}]}, {"name": "man2", "intervals": [{"start": 60000, "end": 65000}]}, {"name": "man6", "intervals": [{"start": 65000, "end": 75000}]}], "predicted_labels": ["start=0ms stop=0ms SPEAKER_00", "start=0ms stop=2000ms SPEAKER_00", "start=2000ms stop=9000ms SPEAKER_00", "start=11000ms stop=12000ms SPEAKER_00", "start=12000ms stop=14000ms SPEAKER_01", "start=14000ms stop=19000ms SPEAKER_01", "start=20000ms stop=36000ms SPEAKER_02", "start=36000ms stop=38000ms SPEAKER_02", "start=41000ms stop=56000ms SPEAKER_02", "start=57000ms stop=60000ms SPEAKER_03", "start=60000ms stop=63000ms SPEAKER_04", "start=64000ms stop=65000ms SPEAKER_04", "start=66000ms stop=67000ms SPEAKER_04", "start=68000ms stop=72000ms SPEAKER_04", "start=73000ms stop=74000ms SPEAKER_04"], "accuracy": 0.733, "number_of_speakers": 6}